LICENSE.txt
MANIFEST.in
README.md
setup.py
Flask_Foundation.egg-info/PKG-INFO
Flask_Foundation.egg-info/SOURCES.txt
Flask_Foundation.egg-info/dependency_links.txt
Flask_Foundation.egg-info/not-zip-safe
Flask_Foundation.egg-info/requires.txt
Flask_Foundation.egg-info/top_level.txt
flask_foundation/__init__.py
flask_foundation/static/css/app.css
flask_foundation/static/css/foundation-icons.css
flask_foundation/static/css/foundation-icons.eot
flask_foundation/static/css/foundation-icons.svg
flask_foundation/static/css/foundation-icons.ttf
flask_foundation/static/css/foundation-icons.woff
flask_foundation/static/css/foundation.css
flask_foundation/static/css/foundation.min.css
flask_foundation/static/css/normalize.css
flask_foundation/static/img/foundation/orbit/bullets.jpg
flask_foundation/static/img/foundation/orbit/left-arrow-small.png
flask_foundation/static/img/foundation/orbit/left-arrow.png
flask_foundation/static/img/foundation/orbit/loading.gif
flask_foundation/static/img/foundation/orbit/mask-black.png
flask_foundation/static/img/foundation/orbit/pause-black.png
flask_foundation/static/img/foundation/orbit/right-arrow-small.png
flask_foundation/static/img/foundation/orbit/right-arrow.png
flask_foundation/static/img/foundation/orbit/rotator-black.png
flask_foundation/static/img/foundation/orbit/timer-black.png
flask_foundation/static/js/app.js
flask_foundation/static/js/foundation.min.js
flask_foundation/static/js/foundation/foundation.abide.js
flask_foundation/static/js/foundation/foundation.accordion.js
flask_foundation/static/js/foundation/foundation.alert.js
flask_foundation/static/js/foundation/foundation.clearing.js
flask_foundation/static/js/foundation/foundation.dropdown.js
flask_foundation/static/js/foundation/foundation.equalizer.js
flask_foundation/static/js/foundation/foundation.interchange.js
flask_foundation/static/js/foundation/foundation.joyride.js
flask_foundation/static/js/foundation/foundation.js
flask_foundation/static/js/foundation/foundation.magellan.js
flask_foundation/static/js/foundation/foundation.offcanvas.js
flask_foundation/static/js/foundation/foundation.orbit.js
flask_foundation/static/js/foundation/foundation.reveal.js
