Metadata-Version: 1.1
Name: Flask-Foundation
Version: 2.1
Summary: An extension that includes the Foundation css framework in your project, without any boilerplate code.
Home-page: http://github.com/brainfire/flask-foundation
Author: Zakaria Zajac
Author-email: zak@brainfi.re
License: BSD
Platform: any
Classifier: Environment :: Web Environment
Classifier: Intended Audience :: Developers
Classifier: License :: OSI Approved :: BSD License
Classifier: Operating System :: OS Independent
Classifier: Programming Language :: Python
Classifier: Programming Language :: Python :: 3
Classifier: Topic :: Internet :: WWW/HTTP :: Dynamic Content
Classifier: Topic :: Software Development :: Libraries :: Python Modules
